{
    "json_Name": "Siberian Husky",
    "json_FCIGruppe": "FCI-Gruppe 5: Spitze und Hunde vom Urtyp",
    "json_Groesse": "Rüden: 53,5 - 60 cm; Hündinnen: 50,5 - 56 cm",
    "json_Verwendung": "Schlittenhund",
    "json_Charakter": "Der Siberian Husky ist ein mittelgroßer Arbeitshund, schnell, leichtfüßig, frei und elegant in der Bewegung. Sein mäßig kompakter, dichtbehaarter Körper, die aufrecht stehenden Ohren und die buschige Rute weisen auf die nordische Herkunft hin. Seine charakteristische Gangart ist fliessend und scheinbar mühelos. Er ist (nach wie vor) äusserst fähig, seine ursprüngliche Aufgabe als Schlittenhund zu erfüllen und leichtere Lasten in mäßigem Tempo über große Entfernungen zu ziehen. Die Proportionen und die Form seines Körpers spiegeln dies grundlegend ausgewogene Verhältnis von Kraft, Schnelligkeit und Ausdauer wieder."
}